sheetview/__init__.py
sheetview/__main__.py
sheetview/viewer.py
sheetview-0.1.0.dist-info/METADATA
sheetview-0.1.0.dist-info/WHEEL
sheetview-0.1.0.dist-info/entry_points.txt
sheetview-0.1.0.dist-info/top_level.txt
sheetview-0.1.0.dist-info/RECORD
