Metadata-Version: 2.4
Name: sheetview
Version: 0.1.0
Summary: View CSV and XLSX files beautifully in your terminal
Home-page: https://github.com/chowdhuryfaizal/sheetview
Author: Chowdhury Faizal Ahammed
Author-email: Chowdhury Faizal Ahammed <chowdhuryfaizal@example.com>
License: MIT
Requires-Python: >=3.8
Requires-Dist: rich>=13.0.0
Requires-Dist: pandas>=2.0.0
Requires-Dist: openpyxl>=3.1.0
